qwen_agent/__init__.py
qwen_agent/agent.py
qwen_agent/log.py
qwen_agent/agents/__init__.py
qwen_agent/agents/article_agent.py
qwen_agent/agents/assistant.py
qwen_agent/agents/docqa_agent.py
qwen_agent/agents/fncall_agent.py
qwen_agent/agents/group_chat.py
qwen_agent/agents/group_chat_auto_router.py
qwen_agent/agents/group_chat_creator.py
qwen_agent/agents/react_chat.py
qwen_agent/agents/router.py
qwen_agent/agents/user_agent.py
qwen_agent/agents/write_from_scratch.py
qwen_agent/llm/__init__.py
qwen_agent/llm/base.py
qwen_agent/llm/function_calling.py
qwen_agent/llm/oai.py
qwen_agent/llm/qwen_dashscope.py
qwen_agent/llm/qwenvl_dashscope.py
qwen_agent/llm/schema.py
qwen_agent/llm/text_base.py
qwen_agent/memory/__init__.py
qwen_agent/memory/memory.py
qwen_agent/prompts/__init__.py
qwen_agent/prompts/continue_writing.py
qwen_agent/prompts/doc_qa.py
qwen_agent/prompts/expand_writing.py
qwen_agent/prompts/gen_keyword.py
qwen_agent/prompts/outline_writing.py
qwen_agent/tools/__init__.py
qwen_agent/tools/amap_weather.py
qwen_agent/tools/base.py
qwen_agent/tools/code_interpreter.py
qwen_agent/tools/doc_parser.py
qwen_agent/tools/image_gen.py
qwen_agent/tools/retrieval.py
qwen_agent/tools/similarity_search.py
qwen_agent/tools/storage.py
qwen_agent/tools/web_extractor.py
qwen_agent/tools/resource/AlibabaPuHuiTi-3-45-Light.ttf
qwen_agent/tools/resource/code_interpreter_init_kernel.py
qwen_agent/tools/resource/image_service.py
qwen_agent/utils/__init__.py
qwen_agent/utils/doc_parser.py
qwen_agent/utils/qwen.tiktoken
qwen_agent/utils/tokenization_qwen.py
qwen_agent/utils/utils.py
qa_test-0.0.6.dist-info/LICENSE
qa_test-0.0.6.dist-info/METADATA
qa_test-0.0.6.dist-info/WHEEL
qa_test-0.0.6.dist-info/top_level.txt
qa_test-0.0.6.dist-info/RECORD
