Metadata-Version: 2.1
Name: qa-test
Version: 0.0.6
Home-page: https://github.com/QwenLM/Qwen-Agent
License-File: LICENSE
Requires-Dist: anyio (>=3.7.1)
Requires-Dist: beautifulsoup4
Requires-Dist: dashscope (>=1.11.0)
Requires-Dist: docx2txt
Requires-Dist: fastapi (>=0.103.1)
Requires-Dist: html2text
Requires-Dist: jieba
Requires-Dist: json5
Requires-Dist: jsonlines
Requires-Dist: jupyter (>=1.0.0)
Requires-Dist: matplotlib
Requires-Dist: numpy
Requires-Dist: openai
Requires-Dist: pandas
Requires-Dist: pdfminer-six
Requires-Dist: pillow
Requires-Dist: pydantic (>=2.3.0)
Requires-Dist: python-pptx
Requires-Dist: seaborn
Requires-Dist: sympy
Requires-Dist: tiktoken
Requires-Dist: unstructured (==0.8.0)
Requires-Dist: uvicorn (>=0.23.2)
